migrate_to_systemd_networkd/__init__.py
migrate_to_systemd_networkd/ifupdown.py
migrate_to_systemd_networkd/utils.py
migrate_to_systemd_networkd-2.1.dist-info/METADATA
migrate_to_systemd_networkd-2.1.dist-info/WHEEL
migrate_to_systemd_networkd-2.1.dist-info/entry_points.txt
migrate_to_systemd_networkd-2.1.dist-info/RECORD
